pyaudiostream/__init__.py
pyaudiostream/__init__.pyi
pyaudiostream/py.typed
pyaudiostream/pyaudiostream.cpython-313-x86_64-linux-gnu.so
pyaudiostream-0.0.3.dist-info/METADATA
pyaudiostream-0.0.3.dist-info/WHEEL
pyaudiostream.libs/libOpenCL-4f604bad.so.1
pyaudiostream.libs/libSvtAv1Enc-2e5a31a7.so.1
pyaudiostream.libs/libX11-xcb-966fc171.so.1
pyaudiostream.libs/libXau-8040da3f.so.6
pyaudiostream.libs/libXdmcp-667d97d6.so.6
pyaudiostream.libs/libXfixes-89e5897f.so.3
pyaudiostream.libs/libaom-2f4f4ed1.so.3
pyaudiostream.libs/libavcodec-8231c9ae.so.60
pyaudiostream.libs/libavformat-5f0970c5.so.60
pyaudiostream.libs/libavutil-11b08364.so.58
pyaudiostream.libs/libblkid-b3d365c3.so.1
pyaudiostream.libs/libbluray-d76b9963.so.2
pyaudiostream.libs/libbrotlicommon-a91ead09.so.1
pyaudiostream.libs/libbrotlidec-64d8a501.so.1
pyaudiostream.libs/libbrotlienc-6e59301f.so.1
pyaudiostream.libs/libbsd-e86cd4f0.so.0
pyaudiostream.libs/libbz2-218c4abd.so.1.0
pyaudiostream.libs/libcairo-3144bd59.so.2
pyaudiostream.libs/libcairo-gobject-61b4b6cb.so.2
pyaudiostream.libs/libchromaprint-6d960c42.so.1
pyaudiostream.libs/libcjson-31e0b2f4.so.1
pyaudiostream.libs/libcodec2-b54a235c.so.1.2
pyaudiostream.libs/libcom_err-022943b3.so.2
pyaudiostream.libs/libcrypto-c19c2cf8.so.3
pyaudiostream.libs/libdatrie-507f33ed.so.1
pyaudiostream.libs/libdav1d-314d5371.so.7
pyaudiostream.libs/libdrm-e34e2ee7.so.2
pyaudiostream.libs/libffi-00f593fe.so.8
pyaudiostream.libs/libfontconfig-a94b4059.so.1
pyaudiostream.libs/libfreetype-fd0e5281.so.6
pyaudiostream.libs/libfribidi-550020af.so.0
pyaudiostream.libs/libgcrypt-f207cbaa.so.20
pyaudiostream.libs/libgdk_pixbuf-2-b6eef350.0.so.0
pyaudiostream.libs/libgio-2-a51b258a.0.so.0
pyaudiostream.libs/libgme-70f3bc01.so.0
pyaudiostream.libs/libgmodule-2-e8c332eb.0.so.0
pyaudiostream.libs/libgmp-0ccdfb6d.so.10
pyaudiostream.libs/libgnutls-96137275.so.30
pyaudiostream.libs/libgomp-16c68465.so.1
pyaudiostream.libs/libgpg-error-6cb18a00.so.0
pyaudiostream.libs/libgraphite2-2034ccc8.so.3
pyaudiostream.libs/libgsm-c2cba796.so.1
pyaudiostream-0.0.3.dist-info/RECORD
