Metadata-Version: 2.4
Name: pyaudiostream
Version: 0.0.3
Requires-Dist: numpy>=1.20
Requires-Python: >=3.8
